sitegate/__init__.py
sitegate/admin.py
sitegate/apps.py
sitegate/decorators.py
sitegate/exceptions.py
sitegate/flows_base.py
sitegate/models.py
sitegate/repo.py
sitegate/settings.py
sitegate/signals.py
sitegate/toolbox.py
sitegate/utils.py
sitegate/views.py
sitegate/locale/cz/LC_MESSAGES/django.mo
sitegate/locale/cz/LC_MESSAGES/django.po
sitegate/locale/en/LC_MESSAGES/django.mo
sitegate/locale/en/LC_MESSAGES/django.po
sitegate/locale/pl/LC_MESSAGES/django.mo
sitegate/locale/pl/LC_MESSAGES/django.po
sitegate/locale/ru/LC_MESSAGES/django.mo
sitegate/locale/ru/LC_MESSAGES/django.po
sitegate/migrations/0001_initial.py
sitegate/migrations/0002_remoterecord.py
sitegate/migrations/__init__.py
sitegate/signin_flows/__init__.py
sitegate/signin_flows/base.py
sitegate/signin_flows/classic.py
sitegate/signin_flows/modern.py
sitegate/signin_flows/remotes/__init__.py
sitegate/signin_flows/remotes/base.py
sitegate/signin_flows/remotes/google.py
sitegate/signin_flows/remotes/yandex.py
sitegate/signup_flows/__init__.py
sitegate/signup_flows/base.py
sitegate/signup_flows/classic.py
sitegate/signup_flows/modern.py
sitegate/templates/sitegate/remotes/generic.html
sitegate/templates/sitegate/signin/_form_base.html
sitegate/templates/sitegate/signin/form_as_p.html
sitegate/templates/sitegate/signin/form_bootstrap.html
sitegate/templates/sitegate/signin/form_bootstrap3.html
sitegate/templates/sitegate/signin/form_bootstrap4.html
sitegate/templates/sitegate/signin/form_bootstrap4_remote.html
sitegate/templates/sitegate/signin/form_foundation.html
sitegate/templates/sitegate/signin/form_remote.html
sitegate/templates/sitegate/signin/form_remotes.html
sitegate/templates/sitegate/signup/_form_base.html
sitegate/templates/sitegate/signup/form_as_p.html
sitegate/templates/sitegate/signup/form_bootstrap.html
sitegate/templates/sitegate/signup/form_bootstrap3.html
sitegate/templates/sitegate/signup/form_bootstrap4.html
sitegate/templates/sitegate/signup/form_foundation.html
django_sitegate-1.3.3.dist-info/AUTHORS
django_sitegate-1.3.3.dist-info/LICENSE
django_sitegate-1.3.3.dist-info/METADATA
django_sitegate-1.3.3.dist-info/WHEEL
django_sitegate-1.3.3.dist-info/top_level.txt
django_sitegate-1.3.3.dist-info/RECORD
