Metadata-Version: 2.1
Name: django-sitegate
Version: 1.3.3
Summary: Reusable application for Django to ease sign up & sign in processes
Home-page: http://github.com/idlesign/django-sitegate
Author: Igor `idle sign` Starikov
Author-email: idlesign@yandex.ru
License: BSD 3-Clause License
Platform: UNKNOWN
Classifier: Development Status :: 5 - Production/Stable
Classifier: Environment :: Web Environment
Classifier: Framework :: Django
Classifier: Intended Audience :: Developers
Classifier: License :: OSI Approved :: BSD License
Classifier: Operating System :: OS Independent
Classifier: Programming Language :: Python
Classifier: Programming Language :: Python :: 3
Classifier: Programming Language :: Python :: 3.7
Classifier: Programming Language :: Python :: 3.8
Classifier: Programming Language :: Python :: 3.9
Classifier: Programming Language :: Python :: 3.10
Requires-Dist: django-etc (>=1.2.0)
Requires-Dist: django-siteprefs (>=1.1.0)
Requires-Dist: requests
